odoo/addons/product_pack_category_restriction/README.rst
odoo/addons/product_pack_category_restriction/__init__.py
odoo/addons/product_pack_category_restriction/__manifest__.py
odoo/addons/product_pack_category_restriction/i18n/it.po
odoo/addons/product_pack_category_restriction/i18n/product_pack_category_restriction.pot
odoo/addons/product_pack_category_restriction/models/__init__.py
odoo/addons/product_pack_category_restriction/models/product_category.py
odoo/addons/product_pack_category_restriction/models/product_product.py
odoo/addons/product_pack_category_restriction/models/product_template.py
odoo/addons/product_pack_category_restriction/readme/CONTRIBUTORS.rst
odoo/addons/product_pack_category_restriction/readme/DESCRIPTION.rst
odoo/addons/product_pack_category_restriction/readme/USAGE.rst
odoo/addons/product_pack_category_restriction/static/description/icon.png
odoo/addons/product_pack_category_restriction/static/description/index.html
odoo/addons/product_pack_category_restriction/tests/__init__.py
odoo/addons/product_pack_category_restriction/tests/test_product_pack_product_category.py
odoo/addons/product_pack_category_restriction/views/product_category_views.xml
odoo13_addon_product_pack_category_restriction-13.0.1.0.1.dev5.dist-info/METADATA
odoo13_addon_product_pack_category_restriction-13.0.1.0.1.dev5.dist-info/WHEEL
odoo13_addon_product_pack_category_restriction-13.0.1.0.1.dev5.dist-info/top_level.txt
odoo13_addon_product_pack_category_restriction-13.0.1.0.1.dev5.dist-info/RECORD
